argo_ams_library/__init__.py
argo_ams_library/ams.py
argo_ams_library/amsexceptions.py
argo_ams_library/amsmsg.py
argo_ams_library/amssubscription.py
argo_ams_library/amstopic.py
argo_ams_library/amsuser.py
argo_ams_library-1.0.0.dist-info/LICENSE
argo_ams_library-1.0.0.dist-info/METADATA
argo_ams_library-1.0.0.dist-info/WHEEL
argo_ams_library-1.0.0.dist-info/top_level.txt
argo_ams_library-1.0.0.dist-info/RECORD
