Metadata-Version: 2.1
Name: argo-ams-library
Version: 1.0.0
Summary: A simple python library for interacting with the ARGO Messaging Service
Home-page: https://github.com/ARGOeu/argo-ams-library
Author: SRCE, GRNET
Author-email: dvrcic@srce.hr, agelos.tsal@gmail.com, kaggis@gmail.com, themiszamani@gmail.com
License: ASL 2.0
Platform: UNKNOWN
Classifier: Development Status :: 5 - Production/Stable
Classifier: License :: OSI Approved :: Apache Software License
Classifier: Operating System :: POSIX
Classifier: Programming Language :: Python :: 2.7
Classifier: Programming Language :: Python :: 3.6
Classifier: Programming Language :: Python :: 3.7
Classifier: Programming Language :: Python :: 3.8
Classifier: Programming Language :: Python :: 3.9
Classifier: Programming Language :: Python :: 3.10
Classifier: Programming Language :: Python :: 3.11
Classifier: Intended Audience :: Developers
Classifier: Topic :: Software Development :: Libraries :: Python Modules
Requires-Dist: requests
